nissaprinterserver/__init__.py
nissaprinterserver/__main__.py
nissaprinterserver/script.py
nissaprinterserver-1.1.dist-info/METADATA
nissaprinterserver-1.1.dist-info/WHEEL
nissaprinterserver-1.1.dist-info/top_level.txt
nissaprinterserver-1.1.dist-info/RECORD
