Metadata-Version: 2.1
Name: nissaprinterserver
Version: 1.1
Summary: Nisssa Makbuz Printer Server
Home-page: http://github.com/coderprofile/nissaprinterserver
Author: Yasin BIKMAZER
Author-email: yasin@nissayazilim.com
License: MIT
Keywords: dotmatrix printer server
Platform: UNKNOWN
Requires-Dist: flask
